<?xml version="1.0"?>
<!DOCTYPE vortaro SYSTEM "../dtd/vokoxml.dtd">

<vortaro>
<art mrk="$Id: b.xml,v 1.7 2015/10/06 02:10:27 revo Exp $">
<kap>
    <ofc>*</ofc><rad>b</rad> <fnt><bib>PIV1</bib></fnt>
</kap>
<subart>
<drv mrk="b.0.konsonanto">
  <kap><tld/></kap>
    <uzo tip="fak">LIN</uzo>
    <uzo tip="fak">GRA</uzo>
    <uzo tip="fak">FON</uzo>
  <snc>    
    <dif>
      <ref tip="dif" cel="konson1.0o">Konsonanto</ref>, vo&ccirc;a <ref
      tip="dif" cel="plosiv.0o">plosiva</ref> <ref tip="dif"
      cel="labial.0o">labialo</ref> [b].
    </dif>
  <trd lng="fr">b<klr> (consonne)</klr></trd>  
  <trd lng="pt">b<klr> (consoante)</klr></trd>
  </snc>
  <snc>
     <dif>
      La dua <ref tip="dif" cel="grafem.0o">grafemo</ref> de la
      Esperanta
      alfabeto, uzata i.a. kiel:
     </dif>
  <trd lng="fr">b<klr> (lettre)</klr></trd>
  <trd lng="pt">b<klr> (letra)</klr></trd>
  <subsnc>
  <uzo tip="fak">MUZ</uzo>
  <dif>
  (maj.) nomo de la sepa tono de la C-ma&jcirc;ora gamo (494 Hz;
  absolut-solfe&gcirc;a si):<ekz> <tld lit="B"/> bemola, diesa</ekz>;
  </dif>
  <trd lng="fr">si</trd>
  </subsnc>
  <subsnc>
  <uzo tip="fak">KEM</uzo>
  <dif>
  (maj.) simbolo de boro:<ekz> <tld lit="B"/></ekz>;
  </dif>
  <trd lng="fr">bore</trd>
  </subsnc>
  <subsnc>
  <uzo tip="fak">FIZ</uzo>
  <dif>
  (maj.) simbolo de magneta fluksdenso:<ekz> <tld lit="B"/></ekz>;
  </dif>
  <trd lng="fr">densit&eacute; de flux <ind>magn&eacute;tique</ind></trd>
  </subsnc>
  </snc>  
</drv>
</subart>

<subart>
<drv mrk="b.0.nomo">
  <kap><tld/>o</kap>
  <snc> 
    <dif>
      Nomo de tiuj <ref tip="dif" cel="fonem.0o">fonemo</ref> kaj
      grafemo.    
    </dif>
  <trd lng="fr">b</trd>
  </snc>
</drv>
</subart>
</art>

<!--
$Log: b.xml,v $
Revision 1.7  2015/10/06 02:10:27  revo
Evandro Avellar: +trd pt

Revision 1.6  2014/04/12 07:10:22  revo
Damien Brucker: aldono (dauxrigo)

Revision 1.5  2014/04/10 16:10:24  revo
Damien Brucker: fak

Revision 1.4  2013/12/30 10:10:18  revo
Damien Brucker: aldono

Revision 1.3  2013/12/28 15:10:14  revo
Damien Brucker: +ref

Revision 1.2  2013/12/28 13:10:19  revo
Damien Brucker: -tajperaro

Revision 1.1  2013/12/27 20:10:15  revo
Damien Brucker: nova artikolo

-->
</vortaro>
