<?xml version="1.0"?>
<!DOCTYPE vortaro SYSTEM "../dtd/vokoxml.dtd">

<vortaro>
<art mrk="$Id: diabet.xml,v 1.22 2015/07/04 08:37:32 revo Exp $">
<kap>
  <ofc>2</ofc>
  <rad>diabet</rad>/o
</kap>
<drv mrk="diabet.0o">
  <kap><tld/>o</kap>
  <uzo tip="fak">MED</uzo>
  <snc>
    <dif>
      <ref tip="lst" cel="san.mal0o.MED"
      lst="voko:malsanoj">Malsano</ref> karakterizata per neasimilado
      kaj perurina ellasado de
      sukero.   
    </dif>
  </snc>
  <trd lng="be">&c_d;&c_y;&c_ja;&c_b;&c_e;&c_t;</trd>
  <trd lng="bg">&c_d;&c_i;&c_a;&c_b;&c_je;&c_t;</trd>
  <trd lng="ca">diabetis</trd>
  <trdgrp lng="cs">
    <trd>diabetes</trd>,
    <trd>úplavice</trd>
  </trdgrp>
  <trdgrp lng="de">
     <trd>Zuckerkrankheit</trd>,
     <trd>Zucker</trd>,
     <trd>Diabetes</trd>,
     <trd>Diabetes mellitus</trd>
  </trdgrp>
  <trd lng="en">diabetes</trd>
  <trd lng="es">diabetes</trd>
  <trd lng="fr">diab&egrave;te</trd>
  <trdgrp lng="hu">
    <trd>cukorbetegs&eacute;g</trd>,
    <trd>diabetesz</trd>
  </trdgrp>
  <trd lng="id">diabetes</trd>
  <trdgrp lng="nl">
    <trd>diabetes</trd>,
    <trd>suikerziekte</trd>
  </trdgrp>
  <trd lng="pl">cukrzyca</trd>
  <trdgrp lng="pt">
    <trd>diabetes</trd>,
    <trd>diabete</trd>
  </trdgrp>
  <trd lng="ru">&c_d;&c_i;&c_a;&c_b;&c_je;&c_t;</trd>
  <trd lng="sk">cukrovka</trd>
  <trd lng="sv">diabetes</trd>
</drv>
</art>
<!--
$Log: diabet.xml,v $
Revision 1.22  2015/07/04 08:37:32  revo
aldono de trd cs per skripto de M. von Laer

Revision 1.21  2014/11/17 11:12:01  revo
Eko Nur Syah Hidayat: +trd id

Revision 1.20  2013/10/09 18:10:59  revo
Wolfram Diestel: ref al lst malsanoj

Revision 1.19  2012/08/04 12:10:25  revo
Marc Rausell: + trd ca

Revision 1.18  2009/06/10 16:30:28  revo
Wieland Pusch: +trd bg

Revision 1.17  2009/06/09 16:31:16  revo
Sebastian Cyprych: +trd pl

Revision 1.16  2007/07/23 16:31:35  revo
Tulio Flores: +tr pt

Revision 1.15  2003/12/13 17:32:21  revo
Dmitri Gabinski: +trd be

Revision 1.14  2003/04/30 16:31:26  revo
-->
</vortaro>
