<?xml version="1.0"?>
<!DOCTYPE vortaro SYSTEM "../dtd/vokoxml.dtd">

<vortaro>
<art mrk="$Id: emulsi1.xml,v 1.10 2015/07/04 08:37:33 revo Exp $">
<kap>
<rad>emulsin</rad>/o
</kap>
<drv mrk="emulsi1.0o">
<kap><tld/>o</kap>
<uzo tip="fak">KEM</uzo>
<snc>
<dif>
Fermento analoga al la diastazo, kiun oni trovas en migdaloj.  
</dif>
</snc>
  <trd lng="be">&c_e;&c_m;&c_u;&c_l;&c_mol;&c_s;&c_ib;&c_n;</trd>
  <trd lng="cs">emulzin</trd>
  <trdgrp lng="de">
     <trd>Emulsin</trd>,
     <trd>Synaptase</trd>
  </trdgrp>
  <trd lng="fr">&eacute;mulsine</trd>
  <trd lng="pt">emulsina</trd>
  <trd lng="ru">&c_e;&c_m;&c_u;&c_l;&c_mol;&c_s;&c_i;&c_n;</trd>
  <trd lng="sk">emulzín</trd>
</drv>
</art>
<!--
$Log: emulsi1.xml,v $
Revision 1.10  2015/07/04 08:37:33  revo
aldono de trd cs per skripto de M. von Laer

Revision 1.9  2015/06/29 16:29:37  revo
aldono de trd sk per skripto de M. von Laer

Revision 1.8  2007/06/28 16:31:43  revo
Tulio Flores: +tr pt

Revision 1.7  2003/12/17 17:31:12  revo
Dmitri Gabinski: +trd be

Revision 1.6  2002/06/15 17:31:11  revo
Ulrich Fellmann: + 2 trd de

Revision 1.5  2001/06/26 18:11:42  revo
Marc Bavant: +trd fr

Revision 1.4  2001/04/11 16:21:12  revo
Yury Finkel: +trd ru

-->
</vortaro>

