<?xml version="1.0"?>
<!DOCTYPE vortaro SYSTEM "../dtd/vokoxml.dtd">

<vortaro>
<art mrk="$Id: grif.xml,v 1.19 2015/07/04 08:37:35 revo Exp $">
<kap>
  <rad>grif</rad>/o
  <fnt>Z</fnt>
</kap>

<drv mrk="grif.0o">
  <kap><tld/>o</kap>
  <snc mrk="grif.0o.ZOO">
    <uzo tip="fak">ZOO</uzo>
    <dif>
      Nomo de diversaj <ref tip="super" cel="bird.rabo0oj">rabobirdoj
      </ref> nutrantaj sin precipe de putra&jcirc;o.
    </dif>
    <refgrp tip="sub">
      <ref cel="vultur.0o">vulturo</ref>,
      <ref cel="kondor.0o">kondoro</ref>,
      <ref cel="gipaet.0o">gipaeto</ref>, k.a.
    </refgrp>
    <trd lng="bg">&c_l;&c_je;&c_sh;&c_o;&c_ja;&c_d;</trd>
    <trd lng="ca">carronyaire<klr> (au)</klr></trd>
    <trd lng="cs">sup</trd>
    <trd lng="de">Geier</trd>
    <trd lng="en">vulture</trd>
    <trd lng="fr">charognard</trd>
    <trd lng="hu">kesely&udblac;</trd>
    <trd lng="it">avvoltoio</trd>
    <trd lng="nl">gier</trd>
    <trd lng="pl">s&eogonek;p</trd>
    <trd lng="pt">abutre</trd>
  </snc>
  <snc mrk="grif.0o.MIT">
    <uzo tip="fak">HER</uzo>
    <uzo tip="fak">MIT</uzo>
    <dif>
      Mita <ref tip="super" cel="monstr.0o.BIO">monstro</ref> el speco
      kun aglaj kapo, flugiloj kaj ungoj, leona korpo, ofte figurata sur
      blazonoj, ornama&jcirc;oj.
    </dif>
    <trd lng="ca">griu</trd>
    <trd lng="de">Greif</trd>
    <trd lng="en">griffin</trd>
    <trd lng="fr">griffon<klr> (myth.)</klr></trd>
    <trd lng="hu">griffmad&aacute;r</trd>
    <trd lng="it">grifone</trd>
    <trd lng="nl">griffoen</trd>
    <trdgrp lng="pl">
      <trd>gryf</trd>,
      <trd>gryfon</trd>
    </trdgrp>
    <trd lng="pt">grifo<klr tip="amb"> (mitologia)</klr></trd>
    <trd lng="ru">&c_g;&c_r;&c_i;&c_f;&c_o;&c_n;</trd>
  </snc>
  <trdgrp lng="cs">
    <trd>Noh</trd>,
    <trd>gryf</trd>
  </trdgrp>
  <trd lng="ru">&c_g;&c_r;&c_i;&c_f;</trd>
  <trdgrp lng="sk">
    <trd>Noh</trd>,
    <trd>gryf</trd>
  </trdgrp>
</drv>
</art>
<!--
$Log: grif.xml,v $
Revision 1.19  2015/07/04 08:37:35  revo
aldono de trd cs per skripto de M. von Laer

Revision 1.18  2015/06/29 16:29:39  revo
aldono de trd sk per skripto de M. von Laer

Revision 1.17  2012/08/19 00:11:24  revo
Marc Rausell: + trd ca

Revision 1.16  2010/06/07 16:30:22  revo
Antonio Codazzi: +trd it

Revision 1.15  2008/06/16 16:53:52  revo
Sebastian Cyprych: +trd pl

Revision 1.14  2007/12/20 17:30:30  revo
Wieland Pusch: +trd bg

Revision 1.13  2005/08/26 16:32:13  revo
Luiz Portella: +trd pt

Revision 1.12  2003/08/06 16:31:39  revo
Jeromo Vasxe: + mrk, retusxis dif mit, reordigis snc, relokis trd fr

Revision 1.11 2002/10/19 18:21:34 revo
Christopher Zervic: + ang (1)

Revision 1.10 2002/01/29 17:32:17 revo
-->
</vortaro>
