<?xml version="1.0"?>
<!DOCTYPE vortaro SYSTEM "../dtd/vokoxml.dtd">

<vortaro>
<art mrk="$Id: helik.xml,v 1.38 2015/07/04 08:37:35 revo Exp $">
<kap>
  <ofc>2</ofc>
  <rad>helik</rad>/o
</kap>

<drv mrk="helik.0o">
  <kap><tld/>o</kap>
  <snc mrk="helik.0o.konkhava">
    <dif>
      Gastropodo havanta firman konkon.
    </dif>
    <ref tip="vid" cel="limak.0o.gastropodo">limako</ref>
    <trd lng="be">&c_s;&c_m;&c_o;&c_w;&c_zh;</trd>  
    <trd lng="bg">&c_o;&c_h;&c_l;&c_ju;&c_v;</trd>
    <trdgrp lng="br">
      <trd>maligorn</trd>,
      <trd>melc'hwedenn-grogennek</trd>
    </trdgrp>
    <trdgrp lng="de">
      <trd>Schnecke</trd>,
      <trd>Geh&auml;useschnecke</trd>
    </trdgrp>
    <trd lng="en">snail</trd>
    <trd lng="es">caracol</trd>
    <trd lng="fr">escargot</trd>
    <trd lng="hu">h&aacute;zas <ind>csiga</ind></trd>
    <trdgrp lng="id">
      <trd>bekicot</trd>,
      <trd>keong</trd>,
      <trd>siput</trd>
    </trdgrp>
    <trdgrp lng="nl">
      <trd>slak<klr tip="ind"> (huisjes-)</klr></trd>,
      <trd>huisjesslak</trd>
    </trdgrp>
    <trd lng="pt">caracol</trd>
    <trd lng="pl">&sacute;limak</trd>
    <trd lng="ru">&c_u;&c_l;&c_i;&c_t;&c_k;&c_a;</trd>
  </snc>
  <snc mrk="helik.0o.genro">
    <uzo tip="fak">ZOO</uzo>
    <dif>
      <ref tip="lst" cel="genr.0o.BIO"
      lst="voko:zoologiaj_genroj">Genro</ref> el la familio <ref
      tip="malprt"
      cel="helike.0oj"><tld/>edoj</ref>
      (<trd lng="la">Helix</trd>).
    </dif>
    <bld lok="../bld/helik.jpg">
      <trd lng="la">Helix pomatia</trd>
    </bld>
    <trd lng="de">Weinbergschnecke</trd>
    <trd lng="en">snail</trd>
    <trd lng="hu">csiga</trd>
    <trd lng="pl">&sacute;limak</trd>
  </snc>
  <snc mrk="helik.0o.ascii">
    <uzo tip="fak">KOMP</uzo>
    <dif>
      Neformala nomo de la signo @
      uzata en programlingvoj kaj retadresoj.
    </dif>
    <ref tip="malprt" cel="aski.0o">Askio</ref>
    <ref tip="sin" cel="po.0-signo">po-signo</ref>
    <trd lng="be">&c_s;&c_m;&c_o;&c_w;&c_zh; <klr>(&c_z;&c_n;&c_a;&c_k; "@")</klr></trd>
    <trd lng="de">Klammeraffe</trd>
    <trdgrp lng="en">
      <trd>at sign</trd>
    </trdgrp>
    <trd lng="es">arroba</trd>
    <trd lng="fr">arobace</trd>
    <trd lng="he">"<ind>&shin;&tet;&resh;&vav;&dalet;&lamed;</ind>"</trd>
    <trd lng="hu">kukac</trd>
    <trdgrp lng="id">
      <trd>"<ind>a</ind>" keong</trd>,
      <trd><ind>tanda</ind> at</trd>
    </trdgrp>
    <trd lng="nl">apenstaart</trd>
    <trdgrp lng="pl">
      <trd>ma&lstroke;pa</trd>,
      <trd>ma&lstroke;pka</trd>,
      <trd>a z ogonkiem</trd>
    </trdgrp>
    <trd lng="pt">arroba<klr tip="amb"> (s&iacute;mbolo; @)</klr></trd>
    <trdgrp lng="ru">
      <trd>&c_u;&c_l;&c_i;&c_t;&c_k;&c_a;</trd>,
      <trd>&c_s;&c_o;&c_b;&c_a;&c_k;&c_a;</trd>,
      <trd>&c_k;&c_o;&c_r;&c_ju;&c_ch;&c_k;&c_a;</trd>
    </trdgrp>
  </snc>
  <trd lng="cs">znak zavináč @</trd>
  <trd lng="he">&het;&yod;&lamed;&zayin;&vav;&fnun;</trd>
  <trd lng="it">chiocciola</trd>
  <trd lng="sk">znak zavináča @</trd>
</drv>

</art>
<!--
$Log: helik.xml,v $
Revision 1.38  2015/07/04 08:37:35  revo
aldono de trd cs per skripto de M. von Laer

Revision 1.37  2015/06/29 16:33:15  revo
aldono de trd sk per skripto de M. von Laer

Revision 1.36  2014/06/29 16:10:15  revo
Eko Nur Syah Hidayat: +id

Revision 1.35  2013/09/01 15:10:41  revo
Wolfram Diestel: referenco al listo zoo genroj

Revision 1.34  2010/11/04 17:31:35  revo
Russ Williams: +trd en (kaj forigi snail por simbolo @ en la angla cxar
tio maloftegas)

Revision 1.33  2009/09/04 16:30:52  revo
Antonio Codazzi: korekt de itala trad.

Revision 1.32  2008/04/22 17:50:14  revo
Sebastian Cyprych: +trd pl

Revision 1.31  2007/12/09 17:30:34  revo
Wieland Pusch: +trd bg

Revision 1.30  2005/10/15 16:31:44  revo
Luiz Portella: +trd pt

-->
</vortaro>
