<?xml version="1.0"?>
<!DOCTYPE vortaro SYSTEM "../dtd/vokoxml.dtd">

<vortaro>
<art mrk="$Id: komod.xml,v 1.18 2015/07/04 08:37:37 revo Exp $">
<kap>
  <ofc>*</ofc>
  <rad>komod</rad>/o <fnt><bib>PV</bib></fnt>
</kap>

<drv mrk="komod.0o">
  <kap><ofc>*</ofc><tld/>o</kap>
  <snc mrk="komod.0o.MEB">
    <dif>
      Meblo, atinganta alton de la brusto, kaj konsistanta el tirkestoj,
      metitaj unu super alia, por konservi tola&jcirc;on, galanteriojn 
      kaj ceterajn:
      <ekz>
        la murojn garnis, sur unu flanko, lar&gcirc;a <tld/>o, ornamcele 
        &scirc;ar&gcirc;ita per vazoj kaj statuetoj
        <fnt><bib>KielAkvo</bib>, <lok>1:3</lok></fnt>.
      </ekz>
    </dif>
  </snc>
  <trd lng="be">&c_k;&c_a;&c_m;&c_o;&c_d;&c_a;</trd>
  <trd lng="bg">&c_s;&c_k;&c_r;&c_i;&c_n;</trd>
  <trd lng="ca">calaixera</trd>
  <trdgrp lng="cs">
    <trd>komoda</trd>,
    <trd>prádelník</trd>
  </trdgrp>
  <trdgrp lng="de">
    <trd>Kommode</trd>,
    <trd>Schubladenkasten</trd>
  </trdgrp>
  <trdgrp lng="en">
    <trd>commode<klr tip="amb"> (furniture)</klr></trd>,
    <trd>chest of drawers</trd>
  </trdgrp>
  <trd lng="fr">commode<klr tip="ind"> (meuble)</klr></trd>
  <trdgrp lng="nl">
    <trd>commode</trd>,
    <trd>ladenkast</trd>
  </trdgrp>
  <trd lng="pt">c&ocirc;moda</trd>
  <trd lng="ru">&c_k;&c_o;&c_m;&c_o;&c_d;</trd>
  <trd lng="sk">bielizník</trd>
</drv>
</art>
<!--
$Log: komod.xml,v $
Revision 1.18  2015/07/04 08:37:37  revo
aldono de trd cs per skripto de M. von Laer

Revision 1.17  2015/06/29 16:33:17  revo
aldono de trd sk per skripto de M. von Laer

Revision 1.16  2011/12/07 20:10:10  revo
Marc Rausell: kataluna traduko

Revision 1.15  2011/01/05 12:10:13  revo
Russ Williams: +trd en klr

Revision 1.14  2009/09/03 16:30:48  revo
Paul Peeraerts: +trd nl

Revision 1.13  2007/12/09 17:31:02  revo
Wieland Pusch: +trd bg

Revision 1.12  2007/07/23 16:30:44  revo
Jeromo Vasxe: + mrk + ekz

Revision 1.11 2007/01/06 17:30:20 revo
Tulio Flores: +tr pt

Revision 1.10 2005/01/09 17:32:21 revo
Marc Bavant: +trd fr

Revision 1.9 2003/01/05 17:34:38 revo
-->
</vortaro>
