<?xml version="1.0"?>
<!DOCTYPE vortaro SYSTEM "../dtd/vokoxml.dtd">

<vortaro>
<art mrk="$Id: ripar.xml,v 1.27 2015/07/04 08:37:42 revo Exp $">
<kap>
<ofc>1</ofc>
<rad>ripar</rad>/i
</kap>
<drv mrk="ripar.0i">
  <kap><tld/>i</kap>
  <gra><vspec>tr</vspec></gra>
  <snc mrk="ripar.0i.KOMUNE">
    <dif>
      Remeti <ref tip="ant" cel="difekt.0i">difektitan</ref> aferon
      en bonan, uzeblan staton:
      <ekz>
        oni dungis &scirc;tonhakistojn kaj &ccirc;arpentistojn
        por renovigi la domon de la Eternulo, anka&ubreve; fera&jcirc;istojn
        kaj kupra&jcirc;istojn por <tld/>i la domon de la Eternulo
        <fnt><bib>MT</bib>, <lok>&Kr2; 24:12</lok></fnt>;
      </ekz>
      <ekz>
        kiam Sanbalat kaj Tobija <klr>...</klr> a&ubreve;dis,
        ke la muregoj de Jerusalem estas <tld/>ataj kaj ke la
        bre&ccirc;oj komencis esti fermataj ili tre ekkoleris
        <fnt><bib>MT</bib>, <lok>&Neh; 4:7</lok></fnt>;
      </ekz>
      <ekz>
        li vidis aliajn du fratojn <klr>...</klr>
        en la &scirc;ipeto kun ilia patro Zebedeo <tld/>antajn
        siajn retojn
        <fnt><bib>NT</bib>, <lok>&Mat; 4:21</lok></fnt>;
      </ekz>
      <ekz>
        mi iris por <tld/>igi mian brakhorlo&gcirc;on
        <fnt><aut>Marjorie Boulton</aut>, <vrk>Dinomanio</vrk>,
        <bib>Monato</bib>, <lok>jaro 1994a, numero 2a</lok></fnt>.
      </ekz>
    </dif>
    <refgrp tip="sub">
      <ref cel="flik.0i">fliki</ref>,
      <ref cel="san.0igi">sanigi</ref>
    </refgrp>
    <refgrp tip="vid">
      <ref cel="korekt.0i">korekti</ref>,
      <ref cel="bon.re0igi">rebonigi</ref>
    </refgrp>
  </snc>
  <trdgrp lng="be">
    <trd>&c_r;&c_a;&c_m;&c_a;&c_n;&c_t;&c_a;&c_v;&c_a;&c_c;&c_mol;</trd>,
    <trd>&c_r;&c_a;&c_p;&c_a;&c_r;&c_a;&c_v;&c_a;&c_c;&c_mol;</trd>
  </trdgrp>
  <trd lng="ca">reparar</trd>
  <trdgrp lng="cs">
    <trd>napravit</trd>,
    <trd>odčinit</trd>,
    <trd>opravit</trd>,
    <trd>opravovat</trd>,
    <trd>spravit</trd>
  </trdgrp>
  <trdgrp lng="de">
    <trd>reparieren</trd>,
    <trd>wiederherstellen</trd>
  </trdgrp>
  <trd lng="en">repair</trd>
  <trdgrp lng="es">
    <trd>reparar</trd>,
    <trd>arreglar<klr> (reparar)</klr></trd>
  </trdgrp>
  <trdgrp lng="fa">
    <trd>&a_t;&a_ayn;&a_m;&f_y;&a_r; &f_k;&a_r;&a_d;&a_n;</trd>,
    <trd>&a_b;&a_A;&a_z;&a_s;&a_A;&a_z;&f_y; &f_k;&a_r;&a_d;&a_n;</trd>,
    <trd>&a_t;&a_r;&a_m;&f_y;&a_m; &f_k;&a_r;&a_d;&a_n;</trd>
  </trdgrp>
  <trdgrp lng="fr">
    <trd>r&eacute;parer</trd>,
    <trd>restaurer<klr tip="amb"> (r&eacute;parer)</klr></trd>
  </trdgrp>
  <trdgrp lng="hu">
    <trd>jav&iacute;t</trd>,
    <trd>helyre&aacute;ll&iacute;t</trd>
  </trdgrp>
  <trdgrp lng="nl">
    <trd>repareren</trd>,
    <trd>herstellen</trd>,
    <trd>maken</trd>
  </trdgrp>
  <trdgrp lng="pl">
    <trd>naprawia&cacute;</trd>,
    <trd>reperowa&cacute;</trd>
  </trdgrp>
  <trdgrp lng="pt">
    <trd>reparar</trd>,
    <trd>consertar</trd>,
    <trd>restaurar</trd>
  </trdgrp>
  <trdgrp lng="ru">
    <trd>&c_ch;&c_i;&c_n;&c_i;&c_t;&c_mol;</trd>,
    <trd>&c_p;&c_o;&c_ch;&c_i;&c_n;&c_i;&c_t;&c_mol;</trd>,
    <trd>&c_r;&c_je;&c_m;&c_o;&c_n;&c_t;&c_i;&c_r;&c_o;&c_v;&c_a;&c_t;&c_mol;</trd>,
    <trd>&c_o;&c_t;&c_r;&c_je;&c_m;&c_o;&c_n;&c_t;&c_i;&c_r;&c_o;&c_v;&c_a;&c_t;&c_mol;</trd>,
    <trd>&c_i;&c_s;&c_p;&c_r;&c_a;&c_v;&c_l;&c_ja;&c_t;&c_mol;</trd>,
    <trd>&c_i;&c_s;&c_p;&c_r;&c_a;&c_v;&c_i;&c_t;&c_mol;</trd>
  </trdgrp>
  <trdgrp lng="sk">
    <trd>napraviť</trd>,
    <trd>odčiniť</trd>,
    <trd>opraviť</trd>
  </trdgrp>
  <trd lng="sv">reparera</trd>
  <trd lng="tp">pona</trd>
</drv>

<drv mrk="ripar.0o">
  <kap><tld/>o</kap>
  <snc mrk="ripar.0o.riparado">
    <ref tip="dif" cel="ripar.0ado.KOMUNE">riparado</ref>
    <trd lng="ca">reparaci&oacute;</trd>
    <trd lng="en">repair</trd>
    <trd lng="es">reparaci&oacute;n</trd>
    <trd lng="hu">jav&iacute;t&aacute;s</trd>
    <trdgrp lng="pl">
      <trd>naprawa</trd>,
      <trd>reperacja</trd>
    </trdgrp>
    <trdgrp lng="ru">
      <trd>&c_r;&c_je;&c_m;&c_o;&c_n;&c_t;</trd>,
      <trd>&c_p;&c_o;&c_ch;&c_i;&c_n;&c_k;&c_a;</trd>
    </trdgrp>
  </snc>
  <snc mrk="ripar.0o.riparajxo">
    <ref tip="dif" cel="ripar.0ajxo.KOMUNE">ripara&jcirc;o</ref>
    <ekz>
      dum la tri pasintaj monatoj la vesto pli eluzi&gcirc;is,
      en diversaj lokoj &gcirc;i vidigis <tld/>ojn kaj flikojn
      <fnt><bib>Marta</bib></fnt>.
    </ekz>
    <trd lng="hu">jav&iacute;t&aacute;s<klr tip="amb"> (helye is)</klr></trd>
  </snc>
  <trdgrp lng="cs">
    <trd>náprava</trd>,
    <trd>odčinění</trd>,
    <trd>oprava</trd>,
    <trd>správka</trd>
  </trdgrp>
  <trd lng="de">Reparatur</trd>
  <trd lng="fr">r&eacute;paration</trd>
  <trdgrp lng="sk">
    <trd>napravenie</trd>,
    <trd>náhrada</trd>,
    <trd>reparácia</trd>
  </trdgrp>
</drv>

<drv mrk="ripar.0ajxo">
  <kap><tld/>a&jcirc;o</kap>
  <snc mrk="ripar.0ajxo.KOMUNE">
    <dif>
      Parto <tld/>ita, remetita en ta&ubreve;gan staton.
    </dif>
  </snc>
  <trd lng="fr">r&eacute;paration<klr tip="amb"> (endroit
  r&eacute;par&eacute;)</klr></trd>
  <trd lng="hu">jav&iacute;tott (alkat)r&eacute;sz</trd>
</drv>

<drv mrk="ripar.0ado">
  <kap><tld/>ado</kap>
  <snc mrk="ripar.0ado.KOMUNE">
    <dif>
      Ago ripari.
    </dif>
  </snc>
  <trdgrp lng="cs">
    <trd>opravování</trd>,
    <trd>provozní údržba</trd>,
    <trd>provádění oprav</trd>
  </trdgrp>
  <trd lng="en">repair</trd>
  <trd lng="es">reparaci&oacute;n</trd>
  <trdgrp lng="fa">
    <trd>&a_t;&a_ayn;&a_m;&f_y;&a_r;</trd>,
    <trd>&a_b;&a_A;&a_z;&a_s;&a_A;&a_z;&f_y;</trd>,
    <trd>&a_t;&a_r;&a_m;&f_y;&a_m;</trd>
  </trdgrp>
  <trd lng="fr">r&eacute;paration<klr tip="amb"> (action)</klr></trd>
  <trd lng="hu">jav&iacute;t&aacute;s</trd>
  <trdgrp lng="pl">
    <trd>naprawa</trd>,
    <trd>reperacja</trd>
  </trdgrp>
  <trdgrp lng="ru">
    <trd>&c_r;&c_je;&c_m;&c_o;&c_n;&c_t;</trd>,
    <trd>&c_p;&c_o;&c_ch;&c_i;&c_n;&c_k;&c_a;</trd>
  </trdgrp>
  <trdgrp lng="sk">
    <trd>opravovanie</trd>,
    <trd>prevádzková údržba</trd>
  </trdgrp>
</drv>

<drv mrk="ripar.0isto">
  <kap><tld/>isto</kap>
  <snc mrk="ripar.0isto.KOMUNE">
    <dif>
      Homo, kiu profesie riparas objektojn, &ccirc;esigas paneojn:
      <ekz>
        la alarmo sonoras <klr>...</klr> kaj <tld/>isto estas sendata
        <fnt><bib>&Scirc;talrato</bib>, <lok>&ccirc;apitro 12a</lok></fnt>.
      </ekz>
    </dif>
  </snc>
  <trd lng="cs">opravář</trd>
  <trd lng="fa">&a_t;&a_ayn;&a_m;&f_y;&a_r;&f_k;&a_A;&a_r;</trd>
  <trdgrp lng="fr">
    <trd>d&eacute;panneur</trd>,
    <trd>r&eacute;parateur</trd>
  </trdgrp>
  <trd lng="pl">konserwator</trd>
  <trdgrp lng="sk">
    <trd>opravár</trd>,
    <trd>údržbár</trd>
  </trdgrp>
</drv>
</art>
<!--
$Log: ripar.xml,v $
Revision 1.27  2015/07/04 08:37:42  revo
aldono de trd cs per skripto de M. von Laer

Revision 1.26  2015/06/29 16:33:22  revo
aldono de trd sk per skripto de M. von Laer

Revision 1.25  2014/09/26 06:10:12  revo
Sebastian Cyprych: +trd pl

Revision 1.24  2012/11/28 21:10:11  revo
Behnam Tabatabai: +trd fa

Revision 1.23  2007/01/07 17:31:49  revo
Russ Williams: +trd tp

Revision 1.22  2006/08/01 16:32:29  revo
Wieland Pusch: +trd de

Revision 1.21  2006/07/05 18:37:10  revo
Raul Salinas Monteagudo: sen-utf8-igita

Revision 1.20  2006/06/25 16:32:28  revo
Raul Salinas Monteagudo: +trd ca,es

Revision 1.19  2006/02/21 17:32:51  revo
Tulio Flores: +trd pt

Revision 1.18  2006/01/02 17:33:08  revo
-->
</vortaro>
